<?xml version="1.0" encoding="UTF-8"?>
<objects serializationModel="Studio.02.02.00">
	<object class="EncodingSetting" id="{0955b64a-bf04-4a77-bd5c-7572a9985868}">
		<property name="encodingFormat">
			<value>3</value>
		</property>
		<property name="quality">
			<value>37</value>
		</property>
		<relationship name="platform">
			<destination>{fa409fc3-c0c8-4121-9494-016e8478cdef}</destination>
		</relationship>
		<relationship name="encodable">
			<destination>{fa409fc3-c0c8-4121-9494-016e8478cdef}</destination>
		</relationship>
	</object>
</objects>
